minibert/__init__.py
minibert/activations.py
minibert/attention.py
minibert/configuration.py
minibert/embeddings.py
minibert/modules.py
tests/__init__.py
tests/test_attention.py
tests/test_minibert.py
minibert-0.2.2.dist-info/LICENSE
minibert-0.2.2.dist-info/METADATA
minibert-0.2.2.dist-info/WHEEL
minibert-0.2.2.dist-info/top_level.txt
minibert-0.2.2.dist-info/RECORD
