Metadata-Version: 2.1
Name: minibert
Version: 0.2.2
Summary: A simplified implementation of BERT
Home-page: https://git-lium.univ-lemans.fr/gcaillaut/minibert
Author: Gaëtan Caillaut
Author-email: gaetan.caillaut@univ-lemans.fr
License: UNKNOWN
Platform: UNKNOWN
Classifier: Programming Language :: Python :: 3
Classifier: License :: OSI Approved
Classifier: Operating System :: OS Independent
Requires-Python: >=3.8
